lite_agent/__init__.py
lite_agent/agent.py
lite_agent/chat_display.py
lite_agent/client.py
lite_agent/constants.py
lite_agent/context.py
lite_agent/loggers.py
lite_agent/message_transfers.py
lite_agent/py.typed
lite_agent/runner.py
lite_agent/processors/__init__.py
lite_agent/processors/completion_event_processor.py
lite_agent/processors/response_event_processor.py
lite_agent/response_handlers/__init__.py
lite_agent/response_handlers/base.py
lite_agent/response_handlers/completion.py
lite_agent/response_handlers/responses.py
lite_agent/stream_handlers/__init__.py
lite_agent/stream_handlers/openai.py
lite_agent/templates/handoffs_source_instructions.xml.j2
lite_agent/templates/handoffs_target_instructions.xml.j2
lite_agent/templates/wait_for_user_instructions.xml.j2
lite_agent/types/__init__.py
lite_agent/types/events.py
lite_agent/types/messages.py
lite_agent/types/tool_calls.py
lite_agent/utils/__init__.py
lite_agent/utils/advanced_message_builder.py
lite_agent/utils/message_builder.py
lite_agent/utils/message_converter.py
lite_agent/utils/message_state_manager.py
lite_agent/utils/metrics.py
lite_agent-0.16.4.dist-info/METADATA
lite_agent-0.16.4.dist-info/WHEEL
lite_agent-0.16.4.dist-info/RECORD
